django_ethereum/__init__.py
django_ethereum/fields.py
django_ethereum/validators.py
django_ethereum-0.0.4.dist-info/METADATA
django_ethereum-0.0.4.dist-info/RECORD
django_ethereum-0.0.4.dist-info/WHEEL
django_ethereum-0.0.4.dist-info/top_level.txt
tests/__init__.py
tests/dummy_test.py
