Metadata-Version: 2.1
Name: django-ethereum
Version: 0.0.4
Summary: Utilities to make it easier to work with Ethereum from your Django app.
Home-page: https://github.com/mikery/django-ethereum/
Author: Mike Ryan
Author-email: mike@backtothelab.io
License: BSD License
Platform: UNKNOWN
